dell/ChangeIdracUserPasswordREDFISH.py
dell/CreateDeleteIdracUsersREDFISH.py
dell/DellSwitchConnectionCollectionREDFISH.py
dell/GetEthernetInterfacesREDFISH.py
dell/InsertLclogCommentREDFISH.py
dell/SetIdracLcSystemAttributesREDFISH.py
dell/SupportAssistCollectionLocalREDFISH.py
dell/SupportAssistCollectionNetworkShareREDFISH.py
dell/__init__.py
idrac/__init__.py
idrac/connect8.py
idrac/idracaccessor.py
idrac/idracclass.py
idrac/objects.py
idrac/update.py
idrac_wrapper-1.4.dist-info/licenses/LICENSE
scripts/__init__.py
scripts/accounts.py
scripts/attribute.py
scripts/dmanage.py
scripts/info.py
scripts/main.py
scripts/network.py
scripts/passthrough.py
scripts/summary.py
scripts/tsr.py
idrac_wrapper-1.4.dist-info/METADATA
idrac_wrapper-1.4.dist-info/WHEEL
idrac_wrapper-1.4.dist-info/entry_points.txt
idrac_wrapper-1.4.dist-info/top_level.txt
idrac_wrapper-1.4.dist-info/RECORD
