Metadata-Version: 2.4
Name: idrac-wrapper
Version: 1.4
Summary: iDRAC redfish library wrapper
Maintainer-email: Gerard Weatherby <gweatherby@uchc.edu>
License-File: LICENSE
Requires-Dist: keyring
Requires-Dist: redfish
Requires-Dist: requests
Requires-Dist: pyyaml
Dynamic: license-file
